odoo/addons/account_invoice_discount_display_amount/README.rst
odoo/addons/account_invoice_discount_display_amount/__init__.py
odoo/addons/account_invoice_discount_display_amount/__manifest__.py
odoo/addons/account_invoice_discount_display_amount/i18n/account_invoice_discount_display_amount.pot
odoo/addons/account_invoice_discount_display_amount/i18n/es.po
odoo/addons/account_invoice_discount_display_amount/i18n/hr.po
odoo/addons/account_invoice_discount_display_amount/i18n/it.po
odoo/addons/account_invoice_discount_display_amount/models/__init__.py
odoo/addons/account_invoice_discount_display_amount/models/account_move.py
odoo/addons/account_invoice_discount_display_amount/models/account_move_line.py
odoo/addons/account_invoice_discount_display_amount/readme/CONFIGURE.md
odoo/addons/account_invoice_discount_display_amount/readme/CONTRIBUTORS.md
odoo/addons/account_invoice_discount_display_amount/readme/DESCRIPTION.md
odoo/addons/account_invoice_discount_display_amount/readme/USAGE.md
odoo/addons/account_invoice_discount_display_amount/report/report_invoice.xml
odoo/addons/account_invoice_discount_display_amount/static/description/icon.png
odoo/addons/account_invoice_discount_display_amount/static/description/index.html
odoo/addons/account_invoice_discount_display_amount/tests/__init__.py
odoo/addons/account_invoice_discount_display_amount/tests/common.py
odoo/addons/account_invoice_discount_display_amount/tests/test_account_move.py
odoo/addons/account_invoice_discount_display_amount/tests/test_account_move_line.py
odoo/addons/account_invoice_discount_display_amount/tests/test_invoice_discount_display_amount.py
odoo/addons/account_invoice_discount_display_amount/views/account_move_views.xml
odoo_addon_account_invoice_discount_display_amount-17.0.1.0.0.2.dist-info/METADATA
odoo_addon_account_invoice_discount_display_amount-17.0.1.0.0.2.dist-info/WHEEL
odoo_addon_account_invoice_discount_display_amount-17.0.1.0.0.2.dist-info/top_level.txt
odoo_addon_account_invoice_discount_display_amount-17.0.1.0.0.2.dist-info/RECORD
