Metadata-Version: 2.1
Name: odoo-addon-account_invoice_discount_display_amount
Version: 17.0.1.0.0.2
Requires-Python: >=3.10
Requires-Dist: odoo>=17.0a,<17.1dev
Summary: Show total discount applied and total without discount on invoices.
Home-page: https://github.com/OCA/account-invoicing
License: AGPL-3
Author: Sygel,Odoo Community Association (OCA)
Author-email: support@odoo-community.org
Classifier: Programming Language :: Python
Classifier: Framework :: Odoo
Classifier: Framework :: Odoo :: 17.0
Classifier: License :: OSI Approved :: GNU Affero General Public License v3
